hell.py
hell-0.4.1.dist-info/LICENSE
hell-0.4.1.dist-info/METADATA
hell-0.4.1.dist-info/WHEEL
hell-0.4.1.dist-info/top_level.txt
hell-0.4.1.dist-info/RECORD
